mollu/__init__.py
mollu/map.py
mollu/propagator.py
mollu/stage.py
mollu-0.0.4.dist-info/LICENSE
mollu-0.0.4.dist-info/METADATA
mollu-0.0.4.dist-info/WHEEL
mollu-0.0.4.dist-info/top_level.txt
mollu-0.0.4.dist-info/RECORD
